setup.py
MyLib_chenzhang_kxd/Test.py
MyLib_chenzhang_kxd/__init__.py
MyLib_chenzhang_kxd.egg-info/PKG-INFO
MyLib_chenzhang_kxd.egg-info/SOURCES.txt
MyLib_chenzhang_kxd.egg-info/dependency_links.txt
MyLib_chenzhang_kxd.egg-info/top_level.txt