Metadata-Version: 1.0
Name: MyLib-chenzhang-kxd
Version: 0.4
Summary: Django Basic Apps
Home-page: http://www.baidu.com
Author: zhangchen
Author-email: 374201603@qq.com
License: UNKNOWN
Platform: UNKNOWN
